Clock_Dividers/ClkDiv.sv
module ClkDiv
(
    input  logic        i_ref_clk,      
    input  logic        i_rst_n,       
    input  logic [7:0]  i_div_ratio,    
    input  logic        i_clk_en,       
    output logic        o_div_clk       
);

    logic        ClK_DIV_EN;      // Internal clock division enable
    logic [7:0]  half_ratio;     // Half of division ratio
    logic [7:0]  counter;        // Counter
    logic        out_div;

    // half ratio
    assign half_ratio = i_div_ratio >> 1;

    // enable only when ratio >= 2
    assign ClK_DIV_EN = i_clk_en && (i_div_ratio != 8'd0) && (i_div_ratio != 8'd1);

    //--------------------------------------------------
    // Clock divider
    //--------------------------------------------------
    always_ff @(posedge i_ref_clk or negedge i_rst_n) begin
        if (!i_rst_n) begin
            out_div <= 1'b0;
            counter <= 8'd0;
        end
        else if (ClK_DIV_EN) begin
            counter <= counter + 8'd1;

            if (counter == 8'd0)
                out_div <= 1'b1;

            else if (counter == half_ratio)
                out_div <= ~out_div;

            else if (counter == i_div_ratio) begin
                out_div <= ~out_div;
                counter <= 8'd1;
            end
        end
    end

    // Bypass if disabled
    assign o_div_clk = ClK_DIV_EN ? out_div : i_ref_clk;

endmodule

Clock_Dividers/ClkDiv_TB.sv
`timescale 1ns/1ps

module ClkDiv_TB;

    logic i_ref_clk;
    logic i_rst_n;
    logic i_clk_en;
    logic [7:0] i_div_ratio;
    logic o_div_clk;

    // DUT
    ClkDiv dut (
        .i_ref_clk(i_ref_clk),
        .i_rst_n(i_rst_n),
        .i_div_ratio(i_div_ratio),
        .i_clk_en(i_clk_en),
        .o_div_clk(o_div_clk)
    );

    //--------------------------------------------------
    // 100 MHz reference clock
    //--------------------------------------------------
    initial i_ref_clk = 0;
    always #5 i_ref_clk = ~i_ref_clk;

    //--------------------------------------------------
    // Dump VCD
    //--------------------------------------------------
    initial begin
        $dumpfile("waveform.vcd");
        $dumpvars(0, ClkDiv_TB);
    end

    //--------------------------------------------------
    // Test sequence
    //--------------------------------------------------
    initial begin
        $display("CLK_DIV TEST START");

        i_rst_n    = 0;
        i_clk_en    = 0;
        i_div_ratio = 0;

        #20;
        i_rst_n = 1;

        //-----------------------------------
        // Test bypass (divider disabled)
        //-----------------------------------
        i_clk_en    = 0;
        i_div_ratio = 8'd4;
        repeat (5) @(posedge i_ref_clk);

        //-----------------------------------
        // Test divide-by-4
        //-----------------------------------
        i_clk_en    = 1;
        i_div_ratio = 8'd4;

        repeat (20) @(posedge i_ref_clk);

        //-----------------------------------
        // Test divide-by-7 (odd divider)
        //-----------------------------------
        i_div_ratio = 8'd7;
        repeat (40) @(posedge i_ref_clk);

        //-----------------------------------
        // Disable divider again
        //-----------------------------------
        i_clk_en = 0;
        repeat (10) @(posedge i_ref_clk);

        $finish;
    end
endmodule

Clock_Dividers/waveform.vcd
$date
	Wed Feb 18 10:45:37 2026
$end
$version
	Icarus Verilog
$end
$timescale
	1ps
$end
$scope module ClkDiv_TB $end
$var wire 1 ! o_div_clk $end
$var reg 1 " i_clk_en $end
$var reg 8 # i_div_ratio [7:0] $end
$var reg 1 $ i_ref_clk $end
$var reg 1 % i_rst_n $end
$scope module dut $end
$var wire 1 & ClK_DIV_EN $end
$var wire 1 " i_clk_en $end
$var wire 8 ' i_div_ratio [7:0] $end
$var wire 1 $ i_ref_clk $end
$var wire 1 % i_rst_n $end
$var wire 1 ! o_div_clk $end
$var wire 8 ( half_ratio [7:0] $end
$var reg 8 ) counter [7:0] $end
$var reg 1 * out_div $end
$upscope $end
$upscope $end
$enddefinitions $end
$comment Show the parameter values. $end
$dumpall
$end
#0
$dumpvars
0*
b0 )
b0 (
b0 '
0&
0%
0$
b0 #
0"
0!
$end
#5000
1!
1$
#10000
0!
0$
#15000
1!
1$
#20000
0!
b10 (
0$
b100 #
b100 '
1%
#25000
1!
1$
#30000
0!
0$
#35000
1!
1$
#40000
0!
0$
#45000
1!
1$
#50000
0!
0$
#55000
1!
1$
#60000
0!
0$
#65000
1&
0!
1"
1$
#70000
0$
#75000
1!
1*
b1 )
1$
#80000
0$
#85000
b10 )
1$
#90000
0$
#95000
0!
0*
b11 )
1$
#100000
0$
#105000
b100 )
1$
#110000
0$
#115000
1!
1*
b1 )
1$
#120000
0$
#125000
b10 )
1$
#130000
0$
#135000
0!
0*
b11 )
1$
#140000
0$
#145000
b100 )
1$
#150000
0$
#155000
1!
1*
b1 )
1$
#160000
0$
#165000
b10 )
1$
#170000
0$
#175000
0!
0*
b11 )
1$
#180000
0$
#185000
b100 )
1$
#190000
0$
#195000
1!
1*
b1 )
1$
#200000
0$
#205000
b10 )
1$
#210000
0$
#215000
0!
0*
b11 )
1$
#220000
0$
#225000
b100 )
1$
#230000
0$
#235000
1!
1*
b1 )
1$
#240000
0$
#245000
b10 )
1$
#250000
0$
#255000
0!
0*
b11 )
1$
#260000
0$
#265000
b100 )
b11 (
b111 #
b111 '
1$
#270000
0$
#275000
b101 )
1$
#280000
0$
#285000
b110 )
1$
#290000
0$
#295000
b111 )
1$
#300000
0$
#305000
1!
1*
b1 )
1$
#310000
0$
#315000
b10 )
1$
#320000
0$
#325000
b11 )
1$
#330000
0$
#335000
0!
0*
b100 )
1$
#340000
0$
#345000
b101 )
1$
#350000
0$
#355000
b110 )
1$
#360000
0$
#365000
b111 )
1$
#370000
0$
#375000
1!
1*
b1 )
1$
#380000
0$
#385000
b10 )
1$
#390000
0$
#395000
b11 )
1$
#400000
0$
#405000
0!
0*
b100 )
1$
#410000
0$
#415000
b101 )
1$
#420000
0$
#425000
b110 )
1$
#430000
0$
#435000
b111 )
1$
#440000
0$
#445000
1!
1*
b1 )
1$
#450000
0$
#455000
b10 )
1$
#460000
0$
#465000
b11 )
1$
#470000
0$
#475000
0!
0*
b100 )
1$
#480000
0$
#485000
b101 )
1$
#490000
0$
#495000
b110 )
1$
#500000
0$
#505000
b111 )
1$
#510000
0$
#515000
1!
1*
b1 )
1$
#520000
0$
#525000
b10 )
1$
#530000
0$
#535000
b11 )
1$
#540000
0$
#545000
0!
0*
b100 )
1$
#550000
0$
#555000
b101 )
1$
#560000
0$
#565000
b110 )
1$
#570000
0$
#575000
b111 )
1$
#580000
0$
#585000
1!
1*
b1 )
1$
#590000
0$
#595000
b10 )
1$
#600000
0$
#605000
b11 )
1$
#610000
0$
#615000
0!
0*
b100 )
1$
#620000
0$
#625000
b101 )
1$
#630000
0$
#635000
b110 )
1$
#640000
0$
#645000
b111 )
1$
#650000
0$
#655000
1!
1*
b1 )
1$
#660000
0$
#665000
b10 )
0&
0"
1$
