Data_Synchronizer/Data_Sync.sv
module Data_Sync
#(
    parameter int BUS_WIDTH  = 8,
    parameter int NUM_STAGES = 2
)
(
    input  logic                    dest_clk,
    input  logic                    dest_rst,           // async active-low
    input  logic                    bus_enable,
    input  logic [BUS_WIDTH-1:0]    unsync_bus,
    output logic [BUS_WIDTH-1:0]    sync_bus,
    output logic                    enable_pulse
);

    // Multi-stage synchronizer per bit
    logic [NUM_STAGES:0] sync_reg [BUS_WIDTH];

    logic [BUS_WIDTH-1:0] flops_out;
    logic [BUS_WIDTH-1:0] flops_pre_out;
    logic [BUS_WIDTH-1:0] generated_enable;

    integer I;

    // Rising-edge detect on synchronized enable
    assign generated_enable = (~flops_out) & flops_pre_out;

    //--------------------------------------------------
    // Sequential logic
    //--------------------------------------------------
    always_ff @(posedge dest_clk or negedge dest_rst) begin
        if (!dest_rst) begin
            sync_bus     <= '0;
            enable_pulse <= 1'b0;
            for (I=0; I<BUS_WIDTH; I++)
                sync_reg[I] <= '0;
        end
        else begin
            enable_pulse <= &generated_enable;

            // Synchronize enable through shift-register per bit
            for (I=0; I<BUS_WIDTH; I++)
                sync_reg[I] <= {bus_enable, sync_reg[I][NUM_STAGES:1]};

            // Latch bus only when all bits are synchronized
            if (&generated_enable)
                sync_bus <= unsync_bus;
        end
    end

    //--------------------------------------------------
    // Extract synchronizer taps
    //--------------------------------------------------
    genvar K;
    generate
        for (K=0; K<BUS_WIDTH; K++) begin
            assign flops_out[K]     = sync_reg[K][0];
            assign flops_pre_out[K] = sync_reg[K][1];
        end
    endgenerate

endmodule

Data_Synchronizer/Data_Sync_TB.sv
`timescale 1ns/1ps

module Data_Sync_TB;

    localparam BUS_WIDTH = 8;

    logic dest_clk;
    logic dest_rst;
    logic bus_enable;
    logic [BUS_WIDTH-1:0] unsync_bus;
    logic [BUS_WIDTH-1:0] sync_bus;
    logic enable_pulse;

    Data_Sync #(.BUS_WIDTH(BUS_WIDTH), .NUM_STAGES(2)) dut (
        .dest_clk(dest_clk),
        .dest_rst(dest_rst),
        .bus_enable(bus_enable),
        .unsync_bus(unsync_bus),
        .sync_bus(sync_bus),
        .enable_pulse(enable_pulse)
    );

    //--------------------------------------------------
    // 100 MHz clock
    //--------------------------------------------------
    initial dest_clk = 0;
    always #5 dest_clk = ~dest_clk;

    //--------------------------------------------------
    // VCD
    //--------------------------------------------------
    initial begin
        $dumpfile("waveform.vcd");
        $dumpvars(0, Data_Sync_TB);
    end

    //--------------------------------------------------
    // Test
    //--------------------------------------------------
    initial begin
        dest_rst = 0;
        bus_enable = 0;
        unsync_bus = 8'h00;
        #20;
        dest_rst = 1;

        //----------------------------------------
        // Apply data
        //----------------------------------------
        unsync_bus = 8'hA5;
        bus_enable = 1;

        // wait for synchronizer (2 cycles)
        repeat (4) @(posedge dest_clk);
        bus_enable = 0;

        //----------------------------------------
        // Change data again
        //----------------------------------------
        unsync_bus = 8'h3C;
        repeat (2) @(posedge dest_clk);

        bus_enable = 1;
        repeat (5) @(posedge dest_clk);

        $finish;
    end

endmodule

Data_Synchronizer/waveform.vcd
$date
	Wed Feb 18 11:31:51 2026
$end
$version
	Icarus Verilog
$end
$timescale
	1ps
$end
$scope module Data_Sync_TB $end
$var wire 8 ! sync_bus [7:0] $end
$var wire 1 " enable_pulse $end
$var parameter 32 # BUS_WIDTH $end
$var reg 1 $ bus_enable $end
$var reg 1 % dest_clk $end
$var reg 1 & dest_rst $end
$var reg 8 ' unsync_bus [7:0] $end
$scope module dut $end
$var wire 1 $ bus_enable $end
$var wire 1 % dest_clk $end
$var wire 1 & dest_rst $end
$var wire 8 ( generated_enable [7:0] $end
$var wire 8 ) unsync_bus [7:0] $end
$var wire 8 * flops_pre_out [7:0] $end
$var wire 8 + flops_out [7:0] $end
$var parameter 32 , BUS_WIDTH $end
$var parameter 32 - NUM_STAGES $end
$var reg 1 " enable_pulse $end
$var reg 8 . sync_bus [7:0] $end
$var integer 32 / I [31:0] $end
$scope begin genblk1[0] $end
$var parameter 2 0 K $end
$upscope $end
$scope begin genblk1[1] $end
$var parameter 2 1 K $end
$upscope $end
$scope begin genblk1[2] $end
$var parameter 3 2 K $end
$upscope $end
$scope begin genblk1[3] $end
$var parameter 3 3 K $end
$upscope $end
$scope begin genblk1[4] $end
$var parameter 4 4 K $end
$upscope $end
$scope begin genblk1[5] $end
$var parameter 4 5 K $end
$upscope $end
$scope begin genblk1[6] $end
$var parameter 4 6 K $end
$upscope $end
$scope begin genblk1[7] $end
$var parameter 4 7 K $end
$upscope $end
$upscope $end
$upscope $end
$enddefinitions $end
$comment Show the parameter values. $end
$dumpall
b111 7
b110 6
b101 5
b100 4
b11 3
b10 2
b1 1
b0 0
b10 -
b1000 ,
b1000 #
$end
#0
$dumpvars
b1000 /
b0 .
b0 +
b0 *
b0 )
b0 (
b0 '
0&
0%
0$
0"
b0 !
$end
#5000
b1000 /
1%
#10000
0%
#15000
b1000 /
1%
#20000
0%
1$
b10100101 '
b10100101 )
1&
#25000
b1000 /
1%
#30000
0%
#35000
b11111111 (
b11111111 *
b1000 /
1%
#40000
0%
#45000
b0 (
b11111111 +
b10100101 !
b10100101 .
1"
b1000 /
1%
#50000
0%
#55000
0"
b1000 /
b111100 '
b111100 )
0$
1%
#60000
0%
#65000
b0 *
b1000 /
1%
#70000
0%
#75000
b0 +
b1000 /
1$
1%
#80000
0%
#85000
b11111111 (
b11111111 *
b1000 /
1%
#90000
0%
#95000
b0 (
b11111111 +
b111100 !
b111100 .
1"
b1000 /
1%
#100000
0%
#105000
0"
b1000 /
1%
#110000
0%
#115000
b1000 /
1%
#120000
0%
#125000
b1000 /
1%
