PULSE_GEN/PULSE_GEN.sv
module PULSE_GEN
(
    input  logic CLK,
    input  logic RST,          // active-low
    input  logic LVL_SIG,
    output logic PULSE_SIG
);

    logic current_flop;
    logic prev_flop;

    //--------------------------------------------------
    // Two-flop synchronizer + edge detector
    //--------------------------------------------------
    always_ff @(posedge CLK or negedge RST) begin
        if (!RST) begin
            current_flop <= 1'b0;
            prev_flop    <= 1'b0;
        end
        else begin
            current_flop <= LVL_SIG;
            prev_flop    <= current_flop;
        end
    end

    // Rising-edge pulse (1-cycle wide)
    assign PULSE_SIG = current_flop & ~prev_flop;

endmodule

PULSE_GEN/PULSE_GEN_TB.sv
`timescale 1ns/1ps

module PULSE_GEN_TB;

    logic CLK;
    logic RST;
    logic LVL_SIG;
    logic PULSE_SIG;

    // DUT
    PULSE_GEN dut (
        .CLK(CLK),
        .RST(RST),
        .LVL_SIG(LVL_SIG),
        .PULSE_SIG(PULSE_SIG)
    );

    //--------------------------------------------------
    // 100 MHz clock
    //--------------------------------------------------
    initial CLK = 0;
    always #5 CLK = ~CLK;

    //--------------------------------------------------
    // VCD
    //--------------------------------------------------
    initial begin
        $dumpfile("waveform.vcd");
        $dumpvars(0, PULSE_GEN_TB);
    end

    //--------------------------------------------------
    // Stimulus
    //--------------------------------------------------
    initial begin
        RST = 0;
        LVL_SIG  = 0;
        #20;
        RST = 1;

        //------------------------------------
        // No pulse when LVL_SIG stays low
        //------------------------------------
        repeat (5) @(posedge CLK);

        //------------------------------------
        // Rising edge → expect 1-cycle pulse
        //------------------------------------
        LVL_SIG = 1;
        repeat (2) @(posedge CLK);

        //------------------------------------
        // Keep LVL_SIG high → no more pulses
        //------------------------------------
        repeat (5) @(posedge CLK);

        //------------------------------------
        // Falling edge → no pulse
        //------------------------------------
        LVL_SIG = 0;
        repeat (3) @(posedge CLK);

        //------------------------------------
        // Rising again → new pulse
        //------------------------------------
        LVL_SIG = 1;
        repeat (2) @(posedge CLK);
        $finish;
    end

endmodule

PULSE_GEN/waveform.vcd
$date
	Wed Feb 18 11:00:22 2026
$end
$version
	Icarus Verilog
$end
$timescale
	1ps
$end
$scope module PULSE_GEN_TB $end
$var wire 1 ! PULSE_SIG $end
$var reg 1 " CLK $end
$var reg 1 # LVL_SIG $end
$var reg 1 $ RST $end
$scope module dut $end
$var wire 1 " CLK $end
$var wire 1 # LVL_SIG $end
$var wire 1 ! PULSE_SIG $end
$var wire 1 $ RST $end
$var reg 1 % current_flop $end
$var reg 1 & prev_flop $end
$upscope $end
$upscope $end
$enddefinitions $end
$comment Show the parameter values. $end
$dumpall
$end
#0
$dumpvars
0&
0%
0$
0#
0"
0!
$end
#5000
1"
#10000
0"
#15000
1"
#20000
0"
1$
#25000
1"
#30000
0"
#35000
1"
#40000
0"
#45000
1"
#50000
0"
#55000
1"
#60000
0"
#65000
1!
1%
1#
1"
#70000
0"
#75000
0!
1&
1"
#80000
0"
#85000
1"
#90000
0"
#95000
1"
#100000
0"
#105000
1"
#110000
0"
#115000
1"
#120000
0"
#125000
1"
#130000
0"
#135000
0%
0#
1"
#140000
0"
#145000
0&
1"
#150000
0"
#155000
1"
#160000
0"
#165000
1!
1%
1#
1"
#170000
0"
#175000
0!
1&
1"
